tap_dayforce/__init__.py
tap_dayforce/streams.py
tap_dayforce/utils.py
tap_dayforce/version.py
tap_dayforce/whitelisting.py
tap_dayforce/schemas/employee_punches.json
tap_dayforce/schemas/employee_raw_punches.json
tap_dayforce/schemas/employees.json
tap_dayforce/schemas/pay_summary_report.json
tap_dayforce-0.3.2.dist-info/LICENSE
tap_dayforce-0.3.2.dist-info/METADATA
tap_dayforce-0.3.2.dist-info/WHEEL
tap_dayforce-0.3.2.dist-info/entry_points.txt
tap_dayforce-0.3.2.dist-info/top_level.txt
tap_dayforce-0.3.2.dist-info/RECORD
